bifrost_bridge/__init__.py
bifrost_bridge/_modidx.py
bifrost_bridge/amrfinderplus.py
bifrost_bridge/bifrost.py
bifrost_bridge/bracken.py
bifrost_bridge/cli.py
bifrost_bridge/core.py
bifrost_bridge/fastp.py
bifrost_bridge/mlst.py
bifrost_bridge/plasmidfinder.py
bifrost_bridge/pmlst.py
bifrost_bridge/quast.py
bifrost_bridge/rmlst.py
bifrost_bridge/shovill.py
bifrost_bridge/ssiamb.py
bifrost_bridge/config/config.default.env
bifrost_bridge/config/config.default.yaml
bifrost_bridge-0.1.0.dist-info/LICENSE
bifrost_bridge-0.1.0.dist-info/METADATA
bifrost_bridge-0.1.0.dist-info/WHEEL
bifrost_bridge-0.1.0.dist-info/entry_points.txt
bifrost_bridge-0.1.0.dist-info/top_level.txt
bifrost_bridge-0.1.0.dist-info/RECORD
