Metadata-Version: 2.1
Name: bifrost_bridge
Version: 0.1.0
Summary: TODO
Home-page: https://github.com/$GIT_USER_NAME/bifrost_bridge
Author: $GIT_USER_NAME
Author-email: povilas.matusevicius@gmail.com
License: MIT License
Keywords: nbdev jupyter notebook python
Classifier: Development Status :: 4 - Beta
Classifier: Intended Audience :: Developers
Classifier: Natural Language :: English
Classifier: Programming Language :: Python :: 3.8
Classifier: Programming Language :: Python :: 3.9
Classifier: Programming Language :: Python :: 3.10
Classifier: Programming Language :: Python :: 3.11
Classifier: Programming Language :: Python :: 3.12
Classifier: License :: OSI Approved :: MIT License
Requires-Python: >=3.8
License-File: LICENSE
Requires-Dist: fastcore
Requires-Dist: python-dotenv
Requires-Dist: envyaml
Requires-Dist: pandas
Requires-Dist: black
Provides-Extra: dev
